test_jmrum/__init__.py
test_jmrum/test_jmrum.py
test_jmrum-0.4.dist-info/LICENSE
test_jmrum-0.4.dist-info/METADATA
test_jmrum-0.4.dist-info/WHEEL
test_jmrum-0.4.dist-info/top_level.txt
test_jmrum-0.4.dist-info/RECORD
